adgodfhkdfh.py
adgodfhkdfh-1.1.0.dist-info/METADATA
adgodfhkdfh-1.1.0.dist-info/WHEEL
adgodfhkdfh-1.1.0.dist-info/top_level.txt
adgodfhkdfh-1.1.0.dist-info/RECORD
