Metadata-Version: 2.1
Name: adgodfhkdfh
Version: 1.1.0
Summary: adgodfhkdfh package
Author: Yonatan Dev
Classifier: Programming Language :: Python :: 3
Classifier: License :: OSI Approved :: MIT License
Classifier: Operating System :: OS Independent
Requires-Python: >=3.6
